[
  {
    "portfolio": "balanced",
    "var_95": -0.0163,
    "sharpe": 1.581,
    "maxdd": -0.1555,
    "kelly": 0.25,
    "real": true
  },
  {
    "portfolio": "ai_infra",
    "var_95": -0.0491,
    "sharpe": 0.894,
    "maxdd": -0.3323,
    "kelly": 0.25,
    "real": true
  },
  {
    "portfolio": "defensive",
    "var_95": -0.0097,
    "sharpe": 1.333,
    "maxdd": -0.103,
    "kelly": 0.25,
    "real": true
  },
  {
    "portfolio": "nuclear",
    "var_95": -0.0563,
    "sharpe": 1.54,
    "maxdd": -0.3705,
    "kelly": 0.25,
    "real": true
  },
  {
    "portfolio": "mag7",
    "var_95": -0.027,
    "sharpe": 0.997,
    "maxdd": -0.2818,
    "kelly": 0.25,
    "real": true
  },
  {
    "portfolio": "pharma",
    "var_95": -0.035,
    "sharpe": -0.035,
    "maxdd": -0.3623,
    "kelly": 0.0,
    "real": true
  },
  {
    "portfolio": "space",
    "var_95": -0.0535,
    "sharpe": 2.284,
    "maxdd": -0.3429,
    "kelly": 0.25,
    "real": true
  },
  {
    "portfolio": "crypto",
    "var_95": -0.0362,
    "sharpe": 0.505,
    "maxdd": -0.3623,
    "kelly": 0.25,
    "real": true
  }
]