[
  {
    "ticker": "MRVL",
    "sentiment": "BULLISH",
    "score": 0.82,
    "reason": "Marvell's new AI partnership and Nvidia's $2\u202fbillion investment signal strong demand for its semiconductor solutions, driving positive investor sentiment.",
    "news_count": 5,
    "latest_headline": "Why Marvell Stock Jumped Today",
    "date": "2026-03-31"
  },
  {
    "ticker": "LUNR",
    "sentiment": "NEUTRAL",
    "score": 0.0,
    "reason": "\nWe need to output JSON with fields sentiment (BULLISH/BEARISH/NEUTRAL), score -1 to 1, reason one s",
    "news_count": 5,
    "latest_headline": "Shares of space-related companies are trading lower as the stock extends Friday's selloff. NASA read",
    "date": "2026-03-31"
  },
  {
    "ticker": "ASTS",
    "sentiment": "NEUTRAL",
    "score": 0.0,
    "reason": "\nWe need to produce JSON with sentiment, score, reason. Determine overall sentiment from news about ",
    "news_count": 5,
    "latest_headline": "Shares of space-related companies are trading lower as the stock extends Friday's selloff. NASA read",
    "date": "2026-03-31"
  },
  {
    "ticker": "DELL",
    "sentiment": "NEUTRAL",
    "score": 0.0,
    "reason": "{\n ",
    "news_count": 5,
    "latest_headline": "Dell Technologies to Present at Bank of America\u2019s View From the Top CEO Series",
    "date": "2026-03-31"
  },
  {
    "ticker": "MRNA",
    "sentiment": "NEUTRAL",
    "score": 0.0,
    "reason": "{\n  \"sentiment\": \"BULLISH\",\n  \"score",
    "news_count": 5,
    "latest_headline": "Cathie Wood Adds 48K Shares to This Under-the-Radar Growth Play",
    "date": "2026-03-31"
  },
  {
    "ticker": "KLAC",
    "sentiment": "NEUTRAL",
    "score": 0.0,
    "reason": "\nWe need to output JSON only with sentiment, score, reason. News items: mostly positive about KLAC: ",
    "news_count": 5,
    "latest_headline": "Why KLA (KLAC) Could Beat Earnings Estimates Again",
    "date": "2026-03-31"
  },
  {
    "ticker": "AMAT",
    "sentiment": "NEUTRAL",
    "score": 0.0,
    "reason": "{\n",
    "news_count": 5,
    "latest_headline": "The AMD Foundation Joins Last Mile Education Fund's National Semiconductor Coalition Protecting Amer",
    "date": "2026-03-31"
  },
  {
    "ticker": "CRCL",
    "sentiment": "NEUTRAL",
    "score": 0.0,
    "reason": "{\"sentiment\":\"BULLISH\",\"score\":0.6,\"reason\":\"Crypto-linked stocks",
    "news_count": 5,
    "latest_headline": "Shares of crypto-related companies are trading higher amid a gain in the price of Bitcoin.",
    "date": "2026-03-31"
  },
  {
    "ticker": "LRCX",
    "sentiment": "NEUTRAL",
    "score": 0.0,
    "reason": "\nWe need to produce JSON with sentiment, score, reason. Evaluate news about LRCX: two items: \"Strong",
    "news_count": 5,
    "latest_headline": "The AMD Foundation Joins Last Mile Education Fund's National Semiconductor Coalition Protecting Amer",
    "date": "2026-03-31"
  },
  {
    "ticker": "MU",
    "sentiment": "NEUTRAL",
    "score": 0.0,
    "reason": "\nWe need to output JSON with sentiment, score, reason. Analyze news about MU. The bullet points:\n\n- ",
    "news_count": 5,
    "latest_headline": "Is It Time To Reconsider Micron Technology (MU) After The Recent Share Price Pullback",
    "date": "2026-03-31"
  }
]